zeus/__init__.py
zeus/_version.py
zeus/autocorr.py
zeus/callbacks.py
zeus/ensemble.py
zeus/fwrapper.py
zeus/moves.py
zeus/parallel.py
zeus/plotting.py
zeus/samples.py
zeus_mcmc-2.5.4.dist-info/METADATA
zeus_mcmc-2.5.4.dist-info/WHEEL
zeus_mcmc-2.5.4.dist-info/top_level.txt
zeus_mcmc-2.5.4.dist-info/RECORD
