Metadata-Version: 2.1
Name: zeus-mcmc
Version: 2.5.4
Summary: zeus: Lightning Fast MCMC
Home-page: https://github.com/minaskar/zeus
Author: Minas Karamanis
Author-email: minaskar@gmail.com
License: GPLv3
Platform: any
Classifier: Programming Language :: Python :: 3
Classifier: License :: OSI Approved :: GNU General Public License v3 (GPLv3)
Classifier: Operating System :: OS Independent
Classifier: Intended Audience :: Science/Research
Classifier: Topic :: Scientific/Engineering
Classifier: Topic :: Scientific/Engineering :: Mathematics
Requires-Python: >=3.7
